pysimplecache/__init__.py
pysimplecache/common/__init__.py
pysimplecache/common/base_serializer.py
pysimplecache/common/json_serializer.py
pysimplecache/providers/__init__.py
pysimplecache/providers/base_provider.py
pysimplecache/providers/memcached.py
pysimplecache/test/__init__.py
pysimplecache/test/memcached_test.py
pysimplecache-0.0.1.dist-info/LICENSE
pysimplecache-0.0.1.dist-info/METADATA
pysimplecache-0.0.1.dist-info/WHEEL
pysimplecache-0.0.1.dist-info/top_level.txt
pysimplecache-0.0.1.dist-info/RECORD
