Metadata-Version: 2.1
Name: pysimplecache
Version: 0.0.1
Summary: A simple caching library for Python
Home-page: https://github.com/stajkowski/simple-cache
Author: Brian Stajkowski
Author-email: stajkowski100@gmail.com
License: UNKNOWN
Platform: UNKNOWN
Classifier: Programming Language :: Python :: 3
Classifier: License :: OSI Approved :: MIT License
Classifier: Operating System :: OS Independent
